linesplit/__init__.py
linesplit/linesplit.py
mkv_line_split-1.0.2.dist-info/LICENSE
mkv_line_split-1.0.2.dist-info/METADATA
mkv_line_split-1.0.2.dist-info/WHEEL
mkv_line_split-1.0.2.dist-info/entry_points.txt
mkv_line_split-1.0.2.dist-info/top_level.txt
mkv_line_split-1.0.2.dist-info/RECORD
