Metadata-Version: 2.1
Name: mkv-line-split
Version: 1.0.2
Summary: Script to split audio lines from .mkv files according to the subtitle
Home-page: https://github.com/awabcodes/mkv-line-splitter
Author: Awab Abdoun
Author-email: awabcodes@gmail.com
License: UNKNOWN
Platform: UNKNOWN
Classifier: Programming Language :: Python :: 3
Classifier: License :: OSI Approved :: MIT License
Classifier: Operating System :: OS Independent
Requires-Dist: tqdm
Requires-Dist: pysubs2
